chialisp_puzzles/__init__.py
chialisp_puzzles/puzzles/calculate_synthetic_public_key.clsp
chialisp_puzzles/puzzles/calculate_synthetic_public_key.hex
chialisp_puzzles/puzzles/p2_conditions.clsp
chialisp_puzzles/puzzles/p2_conditions.hex
chialisp_puzzles/puzzles/p2_delegated_puzzle_or_hidden_puzzle.clsp
chialisp_puzzles/puzzles/p2_delegated_puzzle_or_hidden_puzzle.hex
chialisp_puzzles/puzzles/runtime_build
quex_chialisp_puzzles-0.1.3.dist-info/LICENSE
quex_chialisp_puzzles-0.1.3.dist-info/METADATA
quex_chialisp_puzzles-0.1.3.dist-info/WHEEL
quex_chialisp_puzzles-0.1.3.dist-info/top_level.txt
quex_chialisp_puzzles-0.1.3.dist-info/RECORD
