Metadata-Version: 2.1
Name: quex-chialisp-puzzles
Version: 0.1.3
Summary: Some canonical puzzles deployed on chia-blockchain
Author-email: Richard Kiss <him@richardkiss.com>
License: Copyright 2023 by Richard Kiss
License-File: LICENSE
Requires-Dist: quex-chialisp-loader ==0.1.2
